polka.py
polka-2.5.0.dist-info/WHEEL
polka-2.5.0.dist-info/METADATA
polka-2.5.0.dist-info/RECORD
