Metadata-Version: 2.1
Name: polka
Version: 2.5.0
Summary: A module provides access to the public Polka API. (https://polka.academy/).
Home-page: https://github.com/dmkskn/polka/
License: MIT
Keywords: polka,books,russian,api
Author: Dima Koskin
Author-email: dmksknn@gmail.com
Requires-Python: >=3.6,<4.0
Classifier: License :: OSI Approved :: MIT License
Classifier: Programming Language :: Python
Classifier: Programming Language :: Python :: 3
Classifier: Programming Language :: Python :: 3 :: Only
Classifier: Programming Language :: Python :: 3.6
Classifier: Programming Language :: Python :: 3.7
Classifier: Topic :: Software Development :: Libraries
